pydantic_rpn/__init__.py
pydantic_rpn/cli.py
pydantic_rpn/config.py
pydantic_rpn/core.py
pydantic_rpn/repl.py
pydantic_rpn-2025.9.6.1.dist-info/METADATA
pydantic_rpn-2025.9.6.1.dist-info/WHEEL
pydantic_rpn-2025.9.6.1.dist-info/entry_points.txt
pydantic_rpn-2025.9.6.1.dist-info/licenses/LICENSE
pydantic_rpn-2025.9.6.1.dist-info/RECORD
