Metadata-Version: 2.4
Name: pydantic-rpn
Version: 2025.9.6.1
Summary: A delightful Python library for Reverse Polish Notation with Pydantic integration
Project-URL: Homepage, https://github.com/rsp2k/pydantic-rpn
Project-URL: Repository, https://github.com/rsp2k/pydantic-rpn.git
Project-URL: Documentation, https://github.com/rsp2k/pydantic-rpn#readme
Project-URL: Bug Tracker, https://github.com/rsp2k/pydantic-rpn/issues
Author-email: Claude Code <noreply@anthropic.com>
License: MIT License
License-File: LICENSE
Keywords: calculator,pydantic,reverse-polish-notation,rpn,validation
Classifier: Development Status :: 4 - Beta
Classifier: Intended Audience :: Developers
Classifier: License :: OSI Approved :: MIT License
Classifier: Programming Language :: Python :: 3
Classifier: Programming Language :: Python :: 3.8
Classifier: Programming Language :: Python :: 3.9
Classifier: Programming Language :: Python :: 3.10
Classifier: Programming Language :: Python :: 3.11
Classifier: Programming Language :: Python :: 3.12
Classifier: Topic :: Scientific/Engineering :: Mathematics
Classifier: Topic :: Software Development :: Libraries :: Python Modules
Requires-Python: >=3.8
Requires-Dist: pydantic>=2.0.0
Requires-Dist: typing-extensions>=4.0.0
Provides-Extra: dev
Requires-Dist: hypothesis>=6.0; extra == 'dev'
Requires-Dist: mypy; extra == 'dev'
Requires-Dist: pre-commit; extra == 'dev'
Requires-Dist: pytest-benchmark; extra == 'dev'
Requires-Dist: pytest-cov; extra == 'dev'
Requires-Dist: pytest-xdist; extra == 'dev'
Requires-Dist: pytest>=7.0; extra == 'dev'
Requires-Dist: ruff; extra == 'dev'
Provides-Extra: docs
Requires-Dist: mkdocs; extra == 'docs'
Requires-Dist: mkdocs-material; extra == 'docs'
Requires-Dist: mkdocstrings[python]; extra == 'docs'
Provides-Extra: numpy
Requires-Dist: numpy>=1.20.0; extra == 'numpy'
Provides-Extra: pandas
Requires-Dist: pandas>=1.3.0; extra == 'pandas'
